{
  "1": {
    "validity_ratio": 0.6541666666666667,
    "below": 0,
    "above": 32.600194761580774,
    "turn_on_times": 0,
    "turn_on_ratio": 0.0
  },
  "2": {
    "validity_ratio": 0.6506944444444445,
    "below": -2.4924251959748793,
    "above": 0.8718715571894449,
    "turn_on_times": 1,
    "turn_on_ratio": 1.0
  },
  "3": {
    "validity_ratio": 0.6493055555555556,
    "below": -2.6108103939520797,
    "above": 4.756221519593295,
    "turn_on_times": 0,
    "turn_on_ratio": 0.0
  },
  "4": {
    "validity_ratio": 0.6555555555555556,
    "below": -0.433333333333333,
    "above": 3.7037223854943737,
    "turn_on_times": 0,
    "turn_on_ratio": 0.0
  },
  "5": {
    "validity_ratio": 0.6513888888888889,
    "below": 0,
    "above": 8.446768945815384,
    "turn_on_times": 0,
    "turn_on_ratio": 0.0
  },
  "6": {
    "validity_ratio": 0.65,
    "below": 0,
    "above": 9.223521799258064,
    "turn_on_times": 0,
    "turn_on_ratio": 0.0
  },
  "7": {
    "validity_ratio": 0.6493055555555556,
    "below": -1.7495449712383304,
    "above": 0,
    "turn_on_times": 1,
    "turn_on_ratio": 1.0
  },
  "8": {
    "validity_ratio": 0.6506944444444445,
    "below": -1.7395069789325466,
    "above": 0.028542110156130285,
    "turn_on_times": 2,
    "turn_on_ratio": 1.0
  },
  "9": {
    "validity_ratio": 0.6541666666666667,
    "below": 0,
    "above": 25.425660539400788,
    "turn_on_times": 0,
    "turn_on_ratio": 0.0
  },
  "10": {
    "validity_ratio": 0.6520833333333333,
    "below": 0,
    "above": 0,
    "turn_on_times": 0,
    "turn_on_ratio": 0
  }
}