[
  {
    "timestamp": "2026-03-03-23-57-01",
    "temp": 20.88,
    "hum": 56.45
  },
  {
    "timestamp": "2026-03-03-23-57-01",
    "temp": 20.88,
    "hum": 57.12
  },
  {
    "timestamp": "2026-03-04-00-07-01",
    "temp": 21.04,
    "hum": 57.12
  },
  {
    "timestamp": "2026-03-04-00-07-01",
    "temp": 21.04,
    "hum": 56.72
  },
  {
    "timestamp": "2026-03-04-00-17-02",
    "temp": 21.04,
    "hum": 56.72
  },
  {
    "timestamp": "2026-03-04-00-17-02",
    "temp": 21.04,
    "hum": 56.8
  },
  {
    "timestamp": "2026-03-04-00-27-02",
    "temp": 21.15,
    "hum": 56.8
  },
  {
    "timestamp": "2026-03-04-00-27-02",
    "temp": 21.15,
    "hum": 56.0
  },
  {
    "timestamp": "2026-03-04-00-37-02",
    "temp": 21.19,
    "hum": 56.0
  },
  {
    "timestamp": "2026-03-04-00-37-02",
    "temp": 21.19,
    "hum": 56.2
  },
  {
    "timestamp": "2026-03-04-00-47-02",
    "temp": 21.11,
    "hum": 56.2
  },
  {
    "timestamp": "2026-03-04-00-47-02",
    "temp": 21.11,
    "hum": 56.29
  },
  {
    "timestamp": "2026-03-04-00-57-02",
    "temp": 21.13,
    "hum": 56.29
  },
  {
    "timestamp": "2026-03-04-00-57-02",
    "temp": 21.13,
    "hum": 56.42
  },
  {
    "timestamp": "2026-03-04-01-07-02",
    "temp": 21.04,
    "hum": 56.42
  },
  {
    "timestamp": "2026-03-04-01-07-02",
    "temp": 21.04,
    "hum": 56.33
  },
  {
    "timestamp": "2026-03-04-01-17-03",
    "temp": 20.85,
    "hum": 56.33
  },
  {
    "timestamp": "2026-03-04-01-17-03",
    "temp": 20.85,
    "hum": 56.35
  },
  {
    "timestamp": "2026-03-04-01-27-03",
    "temp": 20.84,
    "hum": 56.35
  },
  {
    "timestamp": "2026-03-04-01-27-03",
    "temp": 20.84,
    "hum": 56.02
  },
  {
    "timestamp": "2026-03-04-01-37-03",
    "temp": 20.88,
    "hum": 56.02
  },
  {
    "timestamp": "2026-03-04-01-37-03",
    "temp": 20.88,
    "hum": 56.33
  },
  {
    "timestamp": "2026-03-04-01-47-03",
    "temp": 20.97,
    "hum": 56.33
  },
  {
    "timestamp": "2026-03-04-01-47-03",
    "temp": 20.97,
    "hum": 57.12
  },
  {
    "timestamp": "2026-03-04-01-57-04",
    "temp": 21.05,
    "hum": 57.12
  },
  {
    "timestamp": "2026-03-04-01-57-04",
    "temp": 21.05,
    "hum": 56.83
  },
  {
    "timestamp": "2026-03-04-02-07-04",
    "temp": 21.2,
    "hum": 56.83
  },
  {
    "timestamp": "2026-03-04-02-07-04",
    "temp": 21.2,
    "hum": 56.2
  },
  {
    "timestamp": "2026-03-04-02-17-04",
    "temp": 21.22,
    "hum": 56.2
  },
  {
    "timestamp": "2026-03-04-02-17-04",
    "temp": 21.22,
    "hum": 56.8
  },
  {
    "timestamp": "2026-03-04-02-27-04",
    "temp": 21.26,
    "hum": 56.8
  },
  {
    "timestamp": "2026-03-04-02-27-04",
    "temp": 21.26,
    "hum": 56.77
  },
  {
    "timestamp": "2026-03-04-02-37-05",
    "temp": 21.37,
    "hum": 56.77
  },
  {
    "timestamp": "2026-03-04-02-37-05",
    "temp": 21.37,
    "hum": 56.17
  },
  {
    "timestamp": "2026-03-04-02-47-05",
    "temp": 21.53,
    "hum": 57.27
  },
  {
    "timestamp": "2026-03-04-02-57-05",
    "temp": 21.45,
    "hum": 57.34
  },
  {
    "timestamp": "2026-03-04-02-57-05",
    "temp": 21.45,
    "hum": 56.17
  },
  {
    "timestamp": "2026-03-04-03-07-05",
    "temp": 21.48,
    "hum": 56.17
  },
  {
    "timestamp": "2026-03-04-03-17-06",
    "temp": 21.44,
    "hum": 56.17
  },
  {
    "timestamp": "2026-03-04-03-17-06",
    "temp": 21.44,
    "hum": 56.57
  },
  {
    "timestamp": "2026-03-04-03-27-06",
    "temp": 21.53,
    "hum": 56.57
  },
  {
    "timestamp": "2026-03-04-03-27-06",
    "temp": 21.53,
    "hum": 55.97
  },
  {
    "timestamp": "2026-03-04-03-37-06",
    "temp": 21.53,
    "hum": 55.97
  },
  {
    "timestamp": "2026-03-04-03-37-06",
    "temp": 21.53,
    "hum": 56.07
  },
  {
    "timestamp": "2026-03-04-03-47-06",
    "temp": 21.66,
    "hum": 56.07
  },
  {
    "timestamp": "2026-03-04-03-47-06",
    "temp": 21.66,
    "hum": 56.17
  },
  {
    "timestamp": "2026-03-04-03-57-07",
    "temp": 21.63,
    "hum": 56.17
  },
  {
    "timestamp": "2026-03-04-03-57-07",
    "temp": 21.63,
    "hum": 56.47
  },
  {
    "timestamp": "2026-03-04-04-07-07",
    "temp": 21.6,
    "hum": 56.47
  },
  {
    "timestamp": "2026-03-04-04-07-07",
    "temp": 21.6,
    "hum": 56.37
  },
  {
    "timestamp": "2026-03-04-04-17-07",
    "temp": 21.7,
    "hum": 56.37
  },
  {
    "timestamp": "2026-03-04-04-17-07",
    "temp": 21.7,
    "hum": 56.44
  },
  {
    "timestamp": "2026-03-04-04-27-07",
    "temp": 21.8,
    "hum": 56.44
  },
  {
    "timestamp": "2026-03-04-04-27-07",
    "temp": 21.8,
    "hum": 56.34
  },
  {
    "timestamp": "2026-03-04-04-37-07",
    "temp": 21.7,
    "hum": 56.34
  },
  {
    "timestamp": "2026-03-04-04-47-08",
    "temp": 21.6,
    "hum": 56.34
  },
  {
    "timestamp": "2026-03-04-04-47-08",
    "temp": 21.6,
    "hum": 56.97
  },
  {
    "timestamp": "2026-03-04-04-57-08",
    "temp": 21.54,
    "hum": 57.17
  },
  {
    "timestamp": "2026-03-04-05-07-08",
    "temp": 21.47,
    "hum": 56.67
  },
  {
    "timestamp": "2026-03-04-05-17-08",
    "temp": 21.44,
    "hum": 57.47
  },
  {
    "timestamp": "2026-03-04-05-17-08",
    "temp": 21.44,
    "hum": 57.5
  },
  {
    "timestamp": "2026-03-04-05-27-09",
    "temp": 21.29,
    "hum": 57.5
  },
  {
    "timestamp": "2026-03-04-05-27-09",
    "temp": 21.29,
    "hum": 57.6
  },
  {
    "timestamp": "2026-03-04-05-37-09",
    "temp": 21.15,
    "hum": 57.6
  },
  {
    "timestamp": "2026-03-04-05-37-09",
    "temp": 21.15,
    "hum": 57.73
  },
  {
    "timestamp": "2026-03-04-05-47-09",
    "temp": 21.1,
    "hum": 57.73
  },
  {
    "timestamp": "2026-03-04-05-47-09",
    "temp": 21.1,
    "hum": 57.33
  },
  {
    "timestamp": "2026-03-04-05-57-09",
    "temp": 21.0,
    "hum": 57.33
  },
  {
    "timestamp": "2026-03-04-06-07-10",
    "temp": 20.94,
    "hum": 57.33
  },
  {
    "timestamp": "2026-03-04-06-07-10",
    "temp": 20.94,
    "hum": 57.05
  },
  {
    "timestamp": "2026-03-04-06-17-10",
    "temp": 20.84,
    "hum": 57.05
  },
  {
    "timestamp": "2026-03-04-06-17-10",
    "temp": 20.84,
    "hum": 57.35
  },
  {
    "timestamp": "2026-03-04-06-27-10",
    "temp": 20.69,
    "hum": 57.35
  },
  {
    "timestamp": "2026-03-04-06-27-10",
    "temp": 20.69,
    "hum": 57.78
  },
  {
    "timestamp": "2026-03-04-06-37-10",
    "temp": 20.57,
    "hum": 57.78
  },
  {
    "timestamp": "2026-03-04-06-37-10",
    "temp": 20.57,
    "hum": 58.49
  },
  {
    "timestamp": "2026-03-04-06-47-10",
    "temp": 20.48,
    "hum": 58.49
  },
  {
    "timestamp": "2026-03-04-06-47-10",
    "temp": 20.48,
    "hum": 57.88
  },
  {
    "timestamp": "2026-03-04-06-57-11",
    "temp": 20.42,
    "hum": 57.88
  },
  {
    "timestamp": "2026-03-04-06-57-11",
    "temp": 20.42,
    "hum": 57.71
  },
  {
    "timestamp": "2026-03-04-07-07-11",
    "temp": 20.34,
    "hum": 57.71
  },
  {
    "timestamp": "2026-03-04-07-07-11",
    "temp": 20.34,
    "hum": 57.91
  },
  {
    "timestamp": "2026-03-04-07-17-11",
    "temp": 20.37,
    "hum": 57.91
  },
  {
    "timestamp": "2026-03-04-07-17-11",
    "temp": 20.37,
    "hum": 58.11
  },
  {
    "timestamp": "2026-03-04-07-27-11",
    "temp": 20.4,
    "hum": 58.11
  },
  {
    "timestamp": "2026-03-04-07-27-11",
    "temp": 20.4,
    "hum": 57.71
  },
  {
    "timestamp": "2026-03-04-07-37-12",
    "temp": 20.37,
    "hum": 58.81
  },
  {
    "timestamp": "2026-03-04-07-37-12",
    "temp": 20.37,
    "hum": 57.51
  },
  {
    "timestamp": "2026-03-04-07-47-12",
    "temp": 20.4,
    "hum": 57.51
  },
  {
    "timestamp": "2026-03-04-07-47-12",
    "temp": 20.4,
    "hum": 58.78
  },
  {
    "timestamp": "2026-03-04-07-57-12",
    "temp": 20.49,
    "hum": 58.78
  },
  {
    "timestamp": "2026-03-04-07-57-12",
    "temp": 20.49,
    "hum": 58.18
  },
  {
    "timestamp": "2026-03-04-08-07-12",
    "temp": 20.49,
    "hum": 58.18
  },
  {
    "timestamp": "2026-03-04-08-17-13",
    "temp": 20.58,
    "hum": 56.78
  },
  {
    "timestamp": "2026-03-04-08-27-13",
    "temp": 20.67,
    "hum": 57.48
  },
  {
    "timestamp": "2026-03-04-08-27-13",
    "temp": 20.67,
    "hum": 56.35
  },
  {
    "timestamp": "2026-03-04-08-37-13",
    "temp": 20.67,
    "hum": 56.35
  },
  {
    "timestamp": "2026-03-04-08-37-13",
    "temp": 20.67,
    "hum": 55.95
  },
  {
    "timestamp": "2026-03-04-08-47-13",
    "temp": 20.58,
    "hum": 55.95
  },
  {
    "timestamp": "2026-03-04-08-47-13",
    "temp": 20.58,
    "hum": 56.25
  },
  {
    "timestamp": "2026-03-04-08-57-14",
    "temp": 20.69,
    "hum": 56.25
  },
  {
    "timestamp": "2026-03-04-08-57-14",
    "temp": 20.69,
    "hum": 56.48
  },
  {
    "timestamp": "2026-03-04-09-07-14",
    "temp": 20.67,
    "hum": 56.48
  },
  {
    "timestamp": "2026-03-04-09-07-14",
    "temp": 20.67,
    "hum": 56.45
  },
  {
    "timestamp": "2026-03-04-09-17-14",
    "temp": 20.77,
    "hum": 56.45
  },
  {
    "timestamp": "2026-03-04-09-17-14",
    "temp": 20.77,
    "hum": 56.02
  },
  {
    "timestamp": "2026-03-04-09-27-14",
    "temp": 20.88,
    "hum": 56.02
  },
  {
    "timestamp": "2026-03-04-09-27-14",
    "temp": 20.88,
    "hum": 55.92
  },
  {
    "timestamp": "2026-03-04-09-37-14",
    "temp": 20.89,
    "hum": 55.92
  },
  {
    "timestamp": "2026-03-04-09-37-14",
    "temp": 20.89,
    "hum": 56.33
  },
  {
    "timestamp": "2026-03-04-09-47-15",
    "temp": 20.84,
    "hum": 56.33
  },
  {
    "timestamp": "2026-03-04-09-47-15",
    "temp": 20.84,
    "hum": 56.25
  },
  {
    "timestamp": "2026-03-04-09-57-15",
    "temp": 20.97,
    "hum": 56.25
  },
  {
    "timestamp": "2026-03-04-09-57-15",
    "temp": 20.97,
    "hum": 56.22
  },
  {
    "timestamp": "2026-03-04-10-07-15",
    "temp": 21.0,
    "hum": 56.22
  },
  {
    "timestamp": "2026-03-04-10-07-15",
    "temp": 21.0,
    "hum": 55.9
  },
  {
    "timestamp": "2026-03-04-10-17-15",
    "temp": 21.2,
    "hum": 55.9
  },
  {
    "timestamp": "2026-03-04-10-17-15",
    "temp": 21.2,
    "hum": 56.02
  },
  {
    "timestamp": "2026-03-04-10-27-15",
    "temp": 21.17,
    "hum": 56.02
  },
  {
    "timestamp": "2026-03-04-10-27-15",
    "temp": 21.17,
    "hum": 56.0
  },
  {
    "timestamp": "2026-03-04-10-37-16",
    "temp": 21.17,
    "hum": 56.0
  },
  {
    "timestamp": "2026-03-04-10-47-16",
    "temp": 21.23,
    "hum": 56.0
  },
  {
    "timestamp": "2026-03-04-10-47-16",
    "temp": 21.23,
    "hum": 55.5
  },
  {
    "timestamp": "2026-03-04-10-57-16",
    "temp": 21.32,
    "hum": 55.5
  },
  {
    "timestamp": "2026-03-04-10-57-16",
    "temp": 21.32,
    "hum": 55.9
  },
  {
    "timestamp": "2026-03-04-11-07-16",
    "temp": 21.3,
    "hum": 55.9
  },
  {
    "timestamp": "2026-03-04-11-07-16",
    "temp": 21.3,
    "hum": 55.7
  },
  {
    "timestamp": "2026-03-04-11-17-17",
    "temp": 21.41,
    "hum": 55.7
  },
  {
    "timestamp": "2026-03-04-11-17-17",
    "temp": 21.41,
    "hum": 56.07
  },
  {
    "timestamp": "2026-03-04-11-27-17",
    "temp": 21.43,
    "hum": 56.07
  },
  {
    "timestamp": "2026-03-04-11-27-17",
    "temp": 21.43,
    "hum": 55.79
  },
  {
    "timestamp": "2026-03-04-11-37-17",
    "temp": 21.44,
    "hum": 55.79
  },
  {
    "timestamp": "2026-03-04-11-37-17",
    "temp": 21.44,
    "hum": 56.37
  },
  {
    "timestamp": "2026-03-04-11-47-17",
    "temp": 21.45,
    "hum": 56.37
  },
  {
    "timestamp": "2026-03-04-11-47-17",
    "temp": 21.45,
    "hum": 56.17
  },
  {
    "timestamp": "2026-03-04-11-57-18",
    "temp": 21.51,
    "hum": 56.17
  },
  {
    "timestamp": "2026-03-04-11-57-18",
    "temp": 21.51,
    "hum": 56.37
  },
  {
    "timestamp": "2026-03-04-12-07-18",
    "temp": 21.44,
    "hum": 56.37
  },
  {
    "timestamp": "2026-03-04-12-07-18",
    "temp": 21.44,
    "hum": 56.17
  },
  {
    "timestamp": "2026-03-04-12-17-18",
    "temp": 21.54,
    "hum": 56.17
  },
  {
    "timestamp": "2026-03-04-12-17-18",
    "temp": 21.54,
    "hum": 56.27
  },
  {
    "timestamp": "2026-03-04-12-27-18",
    "temp": 21.62,
    "hum": 56.27
  },
  {
    "timestamp": "2026-03-04-12-27-18",
    "temp": 21.62,
    "hum": 55.84
  },
  {
    "timestamp": "2026-03-04-12-37-19",
    "temp": 21.65,
    "hum": 55.84
  },
  {
    "timestamp": "2026-03-04-12-47-19",
    "temp": 21.77,
    "hum": 55.84
  },
  {
    "timestamp": "2026-03-04-12-47-19",
    "temp": 21.77,
    "hum": 55.74
  },
  {
    "timestamp": "2026-03-04-12-57-19",
    "temp": 21.84,
    "hum": 55.74
  },
  {
    "timestamp": "2026-03-04-12-57-19",
    "temp": 21.84,
    "hum": 55.84
  },
  {
    "timestamp": "2026-03-04-13-07-19",
    "temp": 21.78,
    "hum": 55.84
  },
  {
    "timestamp": "2026-03-04-13-07-19",
    "temp": 21.78,
    "hum": 55.81
  },
  {
    "timestamp": "2026-03-04-13-17-20",
    "temp": 21.9,
    "hum": 55.81
  },
  {
    "timestamp": "2026-03-04-13-17-20",
    "temp": 21.9,
    "hum": 56.24
  },
  {
    "timestamp": "2026-03-04-13-27-20",
    "temp": 21.85,
    "hum": 56.24
  },
  {
    "timestamp": "2026-03-04-13-27-20",
    "temp": 21.85,
    "hum": 56.01
  },
  {
    "timestamp": "2026-03-04-13-37-20",
    "temp": 21.91,
    "hum": 56.01
  },
  {
    "timestamp": "2026-03-04-13-37-20",
    "temp": 21.91,
    "hum": 55.92
  },
  {
    "timestamp": "2026-03-04-13-47-20",
    "temp": 21.8,
    "hum": 55.92
  },
  {
    "timestamp": "2026-03-04-13-47-20",
    "temp": 21.8,
    "hum": 55.62
  },
  {
    "timestamp": "2026-03-04-13-57-20",
    "temp": 21.81,
    "hum": 55.62
  },
  {
    "timestamp": "2026-03-04-13-57-20",
    "temp": 21.81,
    "hum": 55.71
  },
  {
    "timestamp": "2026-03-04-14-07-21",
    "temp": 21.91,
    "hum": 55.71
  },
  {
    "timestamp": "2026-03-04-14-07-21",
    "temp": 21.91,
    "hum": 55.81
  },
  {
    "timestamp": "2026-03-04-14-17-21",
    "temp": 22.03,
    "hum": 55.81
  },
  {
    "timestamp": "2026-03-04-14-17-21",
    "temp": 22.03,
    "hum": 56.01
  },
  {
    "timestamp": "2026-03-04-14-27-21",
    "temp": 22.03,
    "hum": 56.01
  },
  {
    "timestamp": "2026-03-04-14-27-21",
    "temp": 22.03,
    "hum": 55.71
  },
  {
    "timestamp": "2026-03-04-14-37-21",
    "temp": 22.06,
    "hum": 55.71
  },
  {
    "timestamp": "2026-03-04-14-37-21",
    "temp": 22.06,
    "hum": 55.89
  },
  {
    "timestamp": "2026-03-04-14-47-21",
    "temp": 22.0,
    "hum": 55.89
  },
  {
    "timestamp": "2026-03-04-14-47-21",
    "temp": 22.0,
    "hum": 55.99
  },
  {
    "timestamp": "2026-03-04-14-57-22",
    "temp": 22.13,
    "hum": 55.99
  },
  {
    "timestamp": "2026-03-04-14-57-22",
    "temp": 22.13,
    "hum": 56.09
  },
  {
    "timestamp": "2026-03-04-15-07-22",
    "temp": 22.11,
    "hum": 56.09
  },
  {
    "timestamp": "2026-03-04-15-07-22",
    "temp": 22.11,
    "hum": 57.01
  },
  {
    "timestamp": "2026-03-04-15-17-22",
    "temp": 22.14,
    "hum": 57.01
  },
  {
    "timestamp": "2026-03-04-15-17-22",
    "temp": 22.14,
    "hum": 56.19
  },
  {
    "timestamp": "2026-03-04-15-27-22",
    "temp": 22.17,
    "hum": 57.29
  },
  {
    "timestamp": "2026-03-04-15-37-23",
    "temp": 22.2,
    "hum": 57.29
  },
  {
    "timestamp": "2026-03-04-15-47-23",
    "temp": 22.29,
    "hum": 57.19
  },
  {
    "timestamp": "2026-03-04-15-47-23",
    "temp": 22.29,
    "hum": 58.29
  },
  {
    "timestamp": "2026-03-04-15-57-23",
    "temp": 22.25,
    "hum": 58.29
  },
  {
    "timestamp": "2026-03-04-15-57-23",
    "temp": 22.25,
    "hum": 58.09
  },
  {
    "timestamp": "2026-03-04-16-07-23",
    "temp": 22.21,
    "hum": 58.09
  },
  {
    "timestamp": "2026-03-04-16-07-23",
    "temp": 22.21,
    "hum": 57.89
  },
  {
    "timestamp": "2026-03-04-16-17-24",
    "temp": 22.21,
    "hum": 56.79
  },
  {
    "timestamp": "2026-03-04-16-27-24",
    "temp": 22.18,
    "hum": 57.19
  },
  {
    "timestamp": "2026-03-04-16-37-24",
    "temp": 22.18,
    "hum": 57.52
  },
  {
    "timestamp": "2026-03-04-16-47-24",
    "temp": 22.06,
    "hum": 57.19
  },
  {
    "timestamp": "2026-03-04-16-57-25",
    "temp": 22.06,
    "hum": 57.01
  },
  {
    "timestamp": "2026-03-04-17-07-25",
    "temp": 22.0,
    "hum": 57.22
  },
  {
    "timestamp": "2026-03-04-17-17-25",
    "temp": 21.96,
    "hum": 56.72
  },
  {
    "timestamp": "2026-03-04-17-27-25",
    "temp": 21.96,
    "hum": 56.51
  },
  {
    "timestamp": "2026-03-04-17-37-25",
    "temp": 21.87,
    "hum": 56.62
  },
  {
    "timestamp": "2026-03-04-17-47-26",
    "temp": 21.77,
    "hum": 56.54
  },
  {
    "timestamp": "2026-03-04-17-57-26",
    "temp": 21.7,
    "hum": 57.24
  },
  {
    "timestamp": "2026-03-04-18-07-26",
    "temp": 21.8,
    "hum": 57.74
  },
  {
    "timestamp": "2026-03-04-18-17-26",
    "temp": 21.74,
    "hum": 57.14
  },
  {
    "timestamp": "2026-03-04-18-27-27",
    "temp": 21.7,
    "hum": 58.35
  },
  {
    "timestamp": "2026-03-04-18-37-27",
    "temp": 21.69,
    "hum": 58.05
  },
  {
    "timestamp": "2026-03-04-18-37-27",
    "temp": 21.69,
    "hum": 56.94
  },
  {
    "timestamp": "2026-03-04-18-47-27",
    "temp": 21.58,
    "hum": 56.94
  },
  {
    "timestamp": "2026-03-04-18-47-27",
    "temp": 21.58,
    "hum": 57.24
  },
  {
    "timestamp": "2026-03-04-18-57-27",
    "temp": 21.6,
    "hum": 57.24
  },
  {
    "timestamp": "2026-03-04-18-57-27",
    "temp": 21.6,
    "hum": 56.97
  },
  {
    "timestamp": "2026-03-04-19-07-28",
    "temp": 21.58,
    "hum": 56.97
  },
  {
    "timestamp": "2026-03-04-19-17-28",
    "temp": 21.45,
    "hum": 56.97
  },
  {
    "timestamp": "2026-03-04-19-17-28",
    "temp": 21.45,
    "hum": 57.57
  },
  {
    "timestamp": "2026-03-04-19-27-28",
    "temp": 21.45,
    "hum": 57.57
  },
  {
    "timestamp": "2026-03-04-19-27-28",
    "temp": 21.45,
    "hum": 57.67
  },
  {
    "timestamp": "2026-03-04-19-37-28",
    "temp": 21.51,
    "hum": 57.67
  },
  {
    "timestamp": "2026-03-04-19-37-28",
    "temp": 21.51,
    "hum": 57.37
  },
  {
    "timestamp": "2026-03-04-19-47-29",
    "temp": 21.56,
    "hum": 57.37
  },
  {
    "timestamp": "2026-03-04-19-47-29",
    "temp": 21.56,
    "hum": 57.67
  },
  {
    "timestamp": "2026-03-04-19-57-29",
    "temp": 21.47,
    "hum": 57.67
  },
  {
    "timestamp": "2026-03-04-19-57-29",
    "temp": 21.47,
    "hum": 57.27
  },
  {
    "timestamp": "2026-03-04-20-07-29",
    "temp": 21.44,
    "hum": 57.27
  },
  {
    "timestamp": "2026-03-04-20-07-29",
    "temp": 21.44,
    "hum": 57.57
  },
  {
    "timestamp": "2026-03-04-20-17-29",
    "temp": 21.47,
    "hum": 57.57
  },
  {
    "timestamp": "2026-03-04-20-17-29",
    "temp": 21.47,
    "hum": 57.27
  },
  {
    "timestamp": "2026-03-04-20-27-29",
    "temp": 21.41,
    "hum": 57.27
  },
  {
    "timestamp": "2026-03-04-20-27-29",
    "temp": 21.41,
    "hum": 57.37
  },
  {
    "timestamp": "2026-03-04-20-37-30",
    "temp": 21.48,
    "hum": 56.27
  },
  {
    "timestamp": "2026-03-04-20-37-30",
    "temp": 21.48,
    "hum": 57.27
  },
  {
    "timestamp": "2026-03-04-20-47-30",
    "temp": 21.47,
    "hum": 56.17
  },
  {
    "timestamp": "2026-03-04-20-57-30",
    "temp": 21.35,
    "hum": 56.37
  },
  {
    "timestamp": "2026-03-04-21-07-30",
    "temp": 21.37,
    "hum": 56.87
  },
  {
    "timestamp": "2026-03-04-21-17-31",
    "temp": 21.33,
    "hum": 56.87
  },
  {
    "timestamp": "2026-03-04-21-27-31",
    "temp": 21.35,
    "hum": 56.77
  },
  {
    "timestamp": "2026-03-04-21-37-31",
    "temp": 21.44,
    "hum": 57.07
  },
  {
    "timestamp": "2026-03-04-21-47-31",
    "temp": 21.45,
    "hum": 57.0
  },
  {
    "timestamp": "2026-03-04-21-57-31",
    "temp": 21.4,
    "hum": 55.97
  },
  {
    "timestamp": "2026-03-04-21-57-31",
    "temp": 21.4,
    "hum": 56.07
  },
  {
    "timestamp": "2026-03-04-22-07-32",
    "temp": 21.37,
    "hum": 56.07
  },
  {
    "timestamp": "2026-03-04-22-07-32",
    "temp": 21.37,
    "hum": 56.8
  },
  {
    "timestamp": "2026-03-04-22-17-32",
    "temp": 21.38,
    "hum": 56.8
  },
  {
    "timestamp": "2026-03-04-22-17-32",
    "temp": 21.38,
    "hum": 56.29
  },
  {
    "timestamp": "2026-03-04-22-27-32",
    "temp": 21.35,
    "hum": 57.3
  },
  {
    "timestamp": "2026-03-04-22-27-32",
    "temp": 21.35,
    "hum": 55.9
  },
  {
    "timestamp": "2026-03-04-22-37-32",
    "temp": 21.3,
    "hum": 55.9
  },
  {
    "timestamp": "2026-03-04-22-37-32",
    "temp": 21.3,
    "hum": 56.2
  },
  {
    "timestamp": "2026-03-04-22-47-33",
    "temp": 21.29,
    "hum": 56.2
  },
  {
    "timestamp": "2026-03-04-22-47-33",
    "temp": 21.29,
    "hum": 56.29
  },
  {
    "timestamp": "2026-03-04-22-57-33",
    "temp": 21.29,
    "hum": 56.29
  },
  {
    "timestamp": "2026-03-04-22-57-33",
    "temp": 21.29,
    "hum": 56.4
  },
  {
    "timestamp": "2026-03-04-23-07-33",
    "temp": 21.25,
    "hum": 56.4
  },
  {
    "timestamp": "2026-03-04-23-07-33",
    "temp": 21.25,
    "hum": 56.59
  },
  {
    "timestamp": "2026-03-04-23-17-33",
    "temp": 21.2,
    "hum": 56.59
  }
]