{"timestamp": "2026-02-22-00-00-03", "states": {"1": {"energy_kwh": 51282000.0, "volume_m3": 6524.02197265625, "power_w": 8707.0, "volume_flow_m3h": 0.34200000762939453, "flow_temperature_c": 65.0, "return_temperature_c": 43.0}, "2": {"energy_kwh": 48621000.0, "volume_m3": 7482.47021484375, "power_w": 0.0, "volume_flow_m3h": 0.0, "flow_temperature_c": 54.0, "return_temperature_c": 42.0}, "3": {"energy_kwh": 31030000.0, "volume_m3": 4218.2822265625, "power_w": 446.0, "volume_flow_m3h": 0.017999999225139618, "flow_temperature_c": 68.0, "return_temperature_c": 47.0}, "4": {"energy_kwh": 4916000.0, "volume_m3": 1887.16796875, "power_w": 622.0, "volume_flow_m3h": 0.029999999329447746, "flow_temperature_c": 62.0, "return_temperature_c": 45.0}}}
{"timestamp": "2026-02-22-00-01-03", "states": {"1": {"energy_kwh": 51283000.0, "volume_m3": 6524.033203125, "power_w": 450.0, "volume_flow_m3h": 0.019999999552965164, "flow_temperature_c": 71.0, "return_temperature_c": 42.0}, "2": {"energy_kwh": 48621000.0, "volume_m3": 7482.47021484375, "power_w": 0.0, "volume_flow_m3h": 0.0, "flow_temperature_c": 54.0, "return_temperature_c": 42.0}, "3": {"energy_kwh": 31030000.0, "volume_m3": 4218.2822265625, "power_w": 446.0, "volume_flow_m3h": 0.017999999225139618, "flow_temperature_c": 68.0, "return_temperature_c": 47.0}, "4": {"energy_kwh": 4916000.0, "volume_m3": 1887.16796875, "power_w": 622.0, "volume_flow_m3h": 0.029999999329447746, "flow_temperature_c": 62.0, "return_temperature_c": 45.0}}}
